rabbitmark/__init__.py
rabbitmark/__main__.py
rabbitmark/definitions.py
rabbitmark/cli/__init__.py
rabbitmark/cli/parse.py
rabbitmark/cli/util.py
rabbitmark/gui/__init__.py
rabbitmark/gui/bookmark_table.py
rabbitmark/gui/import_dialog.py
rabbitmark/gui/link_check_dialog.py
rabbitmark/gui/main_window.py
rabbitmark/gui/pocket_import_dialog.py
rabbitmark/gui/utils.py
rabbitmark/gui/wayback_search_dialog.py
rabbitmark/gui/forms/__init__.py
rabbitmark/gui/forms/about.py
rabbitmark/gui/forms/archivesearch.py
rabbitmark/gui/forms/bookmark_details.py
rabbitmark/gui/forms/import_map.py
rabbitmark/gui/forms/linkcheck.py
rabbitmark/gui/forms/linkcheck_progress.py
rabbitmark/gui/forms/main.py
rabbitmark/gui/forms/pocket_import.py
rabbitmark/gui/forms/pocket_preview.py
rabbitmark/gui/forms/resources_rc.py
rabbitmark/librm/__init__.py
rabbitmark/librm/binary_search.py
rabbitmark/librm/bookmark.py
rabbitmark/librm/broken_links.py
rabbitmark/librm/config.py
rabbitmark/librm/database.py
rabbitmark/librm/interchange.py
rabbitmark/librm/models.py
rabbitmark/librm/pocket.py
rabbitmark/librm/tag.py
rabbitmark/librm/wayback_snapshot.py
rabbitmark-0.2.1.dist-info/COPYING
rabbitmark-0.2.1.dist-info/METADATA
rabbitmark-0.2.1.dist-info/WHEEL
rabbitmark-0.2.1.dist-info/entry_points.txt
rabbitmark-0.2.1.dist-info/top_level.txt
rabbitmark-0.2.1.dist-info/RECORD
