Metadata-Version: 2.1
Name: rabbitmark
Version: 0.2.1
Summary: powerful tag-based bookmark manager for the desktop
Home-page: https://github.com/sobjornstad/rabbitmark
Author: Soren I. Bjornstad
Author-email: contact@sorenbjornstad.com
License: UNKNOWN
Platform: UNKNOWN
Classifier: Programming Language :: Python :: 3
Classifier: Programming Language :: Python :: 3.7
Classifier: Programming Language :: Python :: 3.8
Classifier: Programming Language :: Python :: 3.9
Classifier: Programming Language :: Python :: 3.10
Classifier: License :: OSI Approved :: GNU General Public License v3 (GPLv3)
Classifier: Operating System :: OS Independent
Classifier: Topic :: Internet :: WWW/HTTP
Requires-Python: >=3.7
License-File: COPYING
Requires-Dist: SQLAlchemy (~=1.3.5)
Requires-Dist: requests (~=2.21.0)
Requires-Dist: PyQt5 (~=5.15.2)
Requires-Dist: pyperclip (~=1.8.2)
Requires-Dist: tabulate (==0.9.0)
